.gitignore
.travis.yml
MANIFEST.in
README.md
VERSION
__init__.py
dev_requirements.txt
manage.py
pyproject.toml
setup.cfg
setup.py
tox.ini
djangular_serve/.gitignore
djangular_serve/__init__.py
djangular_serve/__main__.py
djangular_serve/__version__.py
djangular_serve/app_settings.py
djangular_serve/apps.py
djangular_serve/consumers.py
djangular_serve/serve.py
djangular_serve/urls.py
djangular_serve/views.py
djangular_serve.egg-info/PKG-INFO
djangular_serve.egg-info/SOURCES.txt
djangular_serve.egg-info/dependency_links.txt
djangular_serve.egg-info/entry_points.txt
djangular_serve.egg-info/top_level.txt
djangular_serve/docs/CREDITS
djangular_serve/docs/license/LICENSE
djangular_serve/docs/license/LICENSE.angular
djangular_serve/docs/license/LICENSE.django
djangular_serve/docs/license/LICENSE.python
djangular_serve/management/__init__.py
djangular_serve/management/exceptions.py
djangular_serve/management/functions.py
djangular_serve/management/handlers.py
djangular_serve/management/utils.py
djangular_serve/migrations/__init__.py
djangular_serve/templates/_index.html
djangular_serve/templates/manifest/fonts.html
djangular_serve/templates/manifest/js.html
djangular_serve/templates/manifest/manifest.json
djangular_serve/templates/manifest/manifest_meta.html
djangular_serve/templates/manifest/offline.html
djangular_serve/templates/manifest/serviceworker.js
djangular_serve/templates/manifest/style.html
djangular_serve/templatetags/__init__.py
djangular_serve/templatetags/serve_tags.py
djangular_serve/tests/__init__.py
djangular_serve/tests/find_ext.py
djangular_serve/tests/test_regex_method.py
djangular_serve/tests/test_serve.py
djangular_serve/tests/tests.txt
example/__init__.py
example/asgi.py
example/db.sqlite3
example/runtest.py
example/settings.py
example/urls.py
example/wsgi.py
example/static/.gitignore
example/templates/_index.html
example/templates/sw.js
example/tests/__init__.py