Metadata-Version: 2.1
Name: djangular-serve
Version: 2.1.0
Summary: Djangular-Serve offers full control and management over Django and Angular PWA.
Home-page: https://github.com/forafekt/djangular-serve
Author: Jonny Doyle
Author-email: jonathan.d@programmer.net
License: MIT
Project-URL: Bug Tracker, https://github.com/forafekt/djangular-serve/issues
Project-URL: Documentation, https://github.com/forafekt/djangular-serve/tree/master/djangular_serve/docs
Project-URL: Source Code, https://github.com/forafekt/djangular-serve
Keywords: django angular client serve pwa template boilerplate git automate djangular python
Platform: UNKNOWN
Classifier: Programming Language :: Python :: 3
Classifier: License :: OSI Approved :: MIT License
Classifier: Operating System :: OS Independent
Classifier: Intended Audience :: Developers
Classifier: Topic :: Software Development :: Build Tools
Requires-Python: >=3.6
